{
	"configurations" : 
	[
		{
			"directories" : 
			[
				{
					"build" : ".",
					"jsonFile" : "directory-.-Debug-d0094a50bb2071803777.json",
					"minimumCMakeVersion" : 
					{
						"string" : "3.21"
					},
					"projectIndex" : 0,
					"source" : ".",
					"targetIndexes" : 
					[
						0,
						1
					]
				}
			],
			"name" : "Debug",
			"projects" : 
			[
				{
					"directoryIndexes" : 
					[
						0
					],
					"name" : "untitled2",
					"targetIndexes" : 
					[
						0,
						1
					]
				}
			],
			"targets" : 
			[
				{
					"directoryIndex" : 0,
					"id" : "target-1::@6890427a1f51a3e7e1df",
					"jsonFile" : "target-target-1-Debug-f14c8ff50d2662924df4.json",
					"name" : "target-1",
					"projectIndex" : 0
				},
				{
					"directoryIndex" : 0,
					"id" : "target_2::@6890427a1f51a3e7e1df",
					"jsonFile" : "target-target_2-Debug-c8c1661ba2181fdceafa.json",
					"name" : "target_2",
					"projectIndex" : 0
				}
			]
		}
	],
	"kind" : "codemodel",
	"paths" : 
	{
		"build" : "C:/Users/ehab/CLionProjects/image_filters1/cmake-build-debug",
		"source" : "C:/Users/ehab/CLionProjects/image_filters1"
	},
	"version" : 
	{
		"major" : 2,
		"minor" : 3
	}
}
